[
  {
    "Type": "PhysicsAsset",
    "Name": "SK_DeadlyGas_PhysicsAsset",
    "Properties": {
      "BoundsBodies": [
        0
      ],
      "SkeletalBodySetups": [
        {
          "ObjectName": "SkeletalBodySetup SK_DeadlyGas_PhysicsAsset:SkeletalBodySetup_0",
          "ObjectPath": "War/Content/Meshes/Weapons/SK_DeadlyGas_PhysicsAsset.1"
        }
      ],
      "ThumbnailInfo": null
    }
  },
  {
    "Type": "SkeletalBodySetup",
    "Name": "SkeletalBodySetup_0",
    "Outer": "SK_DeadlyGas_PhysicsAsset",
    "Properties": {
      "AggGeom": {
        "SphylElems": [
          {
            "Center": {
              "X": 4.3031,
              "Y": -8.265183,
              "Z": -0.14769554
            },
            "Rotation": {
              "Pitch": 0.0,
              "Yaw": 175.18404,
              "Roll": -89.88077
            },
            "Radius": 17.84398,
            "Length": 28.682934,
            "RestOffset": 0.0,
            "Name": "None",
            "bContributeToMass": true
          }
        ]
      },
      "BoneName": "root",
      "CollisionTraceFlag": "CTF_UseSimpleAsComplex"
    }
  }
]