[
  {
    "Type": "PhysicsAsset",
    "Name": "DrawBridge_Physics",
    "Properties": {
      "BoundsBodies": [
        0,
        1
      ],
      "SkeletalBodySetups": [
        {
          "ObjectName": "SkeletalBodySetup DrawBridge_Physics:SkeletalBodySetup_5",
          "ObjectPath": "War/Content/Meshes/Structures/DrawBridge_Physics.2"
        },
        {
          "ObjectName": "SkeletalBodySetup DrawBridge_Physics:SkeletalBodySetup_6",
          "ObjectPath": "War/Content/Meshes/Structures/DrawBridge_Physics.3"
        }
      ],
      "ConstraintSetup": [
        {
          "ObjectName": "PhysicsConstraintTemplate DrawBridge_Physics:PhysicsConstraintTemplate_3",
          "ObjectPath": "War/Content/Meshes/Structures/DrawBridge_Physics.1"
        }
      ],
      "ThumbnailInfo": null
    }
  },
  {
    "Type": "PhysicsConstraintTemplate",
    "Name": "PhysicsConstraintTemplate_3",
    "Outer": "DrawBridge_Physics",
    "Properties": {
      "DefaultInstance": {
        "JointName": "bridge",
        "ConstraintBone1": "bridge",
        "ConstraintBone2": "root",
        "Pos2": {
          "X": 0.0,
          "Y": -8.643905,
          "Z": -1.3287048
        }
      }
    }
  },
  {
    "Type": "SkeletalBodySetup",
    "Name": "SkeletalBodySetup_5",
    "Outer": "DrawBridge_Physics",
    "Properties": {
      "AggGeom": {
        "ConvexElems": [
          {
            "VertexData": [
              {
                "X": -372.25903,
                "Y": -1104.0269,
                "Z": -177.48392
              },
              {
                "X": -372.25922,
                "Y": -55.366333,
                "Z": -177.48392
              },
              {
                "X": -372.25912,
                "Y": -1104.0269,
                "Z": 257.38974
              },
              {
                "X": -372.25922,
                "Y": -55.366333,
                "Z": -29.385803
              },
              {
                "X": -460.3667,
                "Y": -1104.0269,
                "Z": -177.48393
              },
              {
                "X": -460.36688,
                "Y": -55.366333,
                "Z": -177.48393
              },
              {
                "X": -460.36676,
                "Y": -1104.0269,
                "Z": 257.3897
              },
              {
                "X": -460.36688,
                "Y": -362.5114,
                "Z": 257.3897
              },
              {
                "X": -372.25922,
                "Y": -362.5114,
                "Z": 257.38974
              },
              {
                "X": -460.36688,
                "Y": -55.366333,
                "Z": -29.385826
              },
              {
                "X": -372.25906,
                "Y": -1104.0269,
                "Z": -27.650879
              },
              {
                "X": -460.36673,
                "Y": -1104.0269,
                "Z": -27.650887
              }
            ],
            "ElemBox": {
              "Min": {
                "X": -460.36688,
                "Y": -1104.0269,
                "Z": -177.48393
              },
              "Max": {
                "X": -372.25903,
                "Y": -55.366333,
                "Z": 257.38974
              },
              "IsValid": 1
            },
            "Transform": {
              "Rotation": {
                "X": 0.0,
                "Y": 0.0,
                "Z": 0.0,
                "W": 1.0,
                "SizeSquared": 1.0,
                "Size": 1.0,
                "IsNormalized": true
              },
              "Translation": {
                "X": 0.0,
                "Y": 0.0,
                "Z": 0.0
              },
              "Scale3D": {
                "X": 1.0,
                "Y": 1.0,
                "Z": 1.0
              }
            },
            "RestOffset": 0.0,
            "Name": "None",
            "bContributeToMass": true
          },
          {
            "VertexData": [
              {
                "X": 372.25903,
                "Y": -1104.0269,
                "Z": -177.48392
              },
              {
                "X": 372.25906,
                "Y": -1104.0269,
                "Z": -27.650879
              },
              {
                "X": 372.25922,
                "Y": -55.366333,
                "Z": -29.385803
              },
              {
                "X": 372.25922,
                "Y": -55.366333,
                "Z": -177.48392
              },
              {
                "X": 460.3667,
                "Y": -1104.0269,
                "Z": -177.48393
              },
              {
                "X": 460.36688,
                "Y": -55.366333,
                "Z": -177.48393
              },
              {
                "X": 460.36688,
                "Y": -55.366333,
                "Z": -29.385826
              },
              {
                "X": 460.36673,
                "Y": -1104.0269,
                "Z": -27.650887
              },
              {
                "X": 372.25922,
                "Y": -362.5114,
                "Z": 257.38974
              },
              {
                "X": 372.25912,
                "Y": -1104.0269,
                "Z": 257.38974
              },
              {
                "X": 460.36676,
                "Y": -1104.0269,
                "Z": 257.3897
              },
              {
                "X": 460.36688,
                "Y": -362.5114,
                "Z": 257.3897
              }
            ],
            "ElemBox": {
              "Min": {
                "X": 372.25903,
                "Y": -1104.0269,
                "Z": -177.48393
              },
              "Max": {
                "X": 460.36688,
                "Y": -55.366333,
                "Z": 257.38974
              },
              "IsValid": 1
            },
            "Transform": {
              "Rotation": {
                "X": 0.0,
                "Y": 0.0,
                "Z": 0.0,
                "W": 1.0,
                "SizeSquared": 1.0,
                "Size": 1.0,
                "IsNormalized": true
              },
              "Translation": {
                "X": 0.0,
                "Y": 0.0,
                "Z": 0.0
              },
              "Scale3D": {
                "X": 1.0,
                "Y": 1.0,
                "Z": 1.0
              }
            },
            "RestOffset": 0.0,
            "Name": "None",
            "bContributeToMass": true
          },
          {
            "VertexData": [
              {
                "X": -408.18976,
                "Y": -2.1324754,
                "Z": 1.6670284
              },
              {
                "X": 408.18976,
                "Y": -2.1324754,
                "Z": 1.6670284
              },
              {
                "X": -408.18976,
                "Y": -1080.0,
                "Z": 1.6670284
              },
              {
                "X": 408.18976,
                "Y": -1080.0,
                "Z": 1.6670284
              },
              {
                "X": -408.18976,
                "Y": -1080.0,
                "Z": -197.71092
              },
              {
                "X": 408.18976,
                "Y": -1080.0,
                "Z": -197.55249
              },
              {
                "X": -408.18976,
                "Y": -2.1324754,
                "Z": -277.75195
              },
              {
                "X": 408.18976,
                "Y": -2.1324754,
                "Z": -277.5935
              }
            ],
            "ElemBox": {
              "Min": {
                "X": -408.18976,
                "Y": -1080.0,
                "Z": -277.75195
              },
              "Max": {
                "X": 408.18976,
                "Y": -2.1324754,
                "Z": 1.6670284
              },
              "IsValid": 1
            },
            "Transform": {
              "Rotation": {
                "X": 0.0,
                "Y": 0.0,
                "Z": 0.0,
                "W": 1.0,
                "SizeSquared": 1.0,
                "Size": 1.0,
                "IsNormalized": true
              },
              "Translation": {
                "X": 0.0,
                "Y": 0.0,
                "Z": 0.0
              },
              "Scale3D": {
                "X": 1.0,
                "Y": 1.0,
                "Z": 1.0
              }
            },
            "RestOffset": 0.0,
            "Name": "None",
            "bContributeToMass": true
          }
        ]
      },
      "BoneName": "bridge",
      "CollisionTraceFlag": "CTF_UseSimpleAsComplex"
    }
  },
  {
    "Type": "SkeletalBodySetup",
    "Name": "SkeletalBodySetup_6",
    "Outer": "DrawBridge_Physics",
    "Properties": {
      "AggGeom": {
        "ConvexElems": [
          {
            "VertexData": [
              {
                "X": -593.3437,
                "Y": 256.46326,
                "Z": 3.8466797
              },
              {
                "X": -362.7547,
                "Y": 350.57214,
                "Z": 3.8466797
              },
              {
                "X": -362.7547,
                "Y": -12.361816,
                "Z": 3.8466797
              },
              {
                "X": -503.1043,
                "Y": -12.361816,
                "Z": 3.8466797
              },
              {
                "X": -503.1043,
                "Y": 350.57214,
                "Z": 3.8466797
              },
              {
                "X": -593.3437,
                "Y": 81.74707,
                "Z": 3.8466797
              },
              {
                "X": -593.3437,
                "Y": 256.46326,
                "Z": -1024.8474
              },
              {
                "X": -362.7547,
                "Y": 350.57214,
                "Z": -1024.8474
              },
              {
                "X": -362.7547,
                "Y": -12.361816,
                "Z": -1024.8474
              },
              {
                "X": -503.1043,
                "Y": -12.361816,
                "Z": -1024.8474
              },
              {
                "X": -503.1043,
                "Y": 350.57214,
                "Z": -1024.8474
              },
              {
                "X": -593.3437,
                "Y": 81.74707,
                "Z": -1024.8474
              }
            ],
            "ElemBox": {
              "Min": {
                "X": -593.3437,
                "Y": -12.361816,
                "Z": -1024.8474
              },
              "Max": {
                "X": -362.7547,
                "Y": 350.57214,
                "Z": 3.8466797
              },
              "IsValid": 1
            },
            "Transform": {
              "Rotation": {
                "X": 0.0,
                "Y": 0.0,
                "Z": 0.0,
                "W": 1.0,
                "SizeSquared": 1.0,
                "Size": 1.0,
                "IsNormalized": true
              },
              "Translation": {
                "X": 0.0,
                "Y": 0.0,
                "Z": 0.0
              },
              "Scale3D": {
                "X": 1.0,
                "Y": 1.0,
                "Z": 1.0
              }
            },
            "RestOffset": 0.0,
            "Name": "None",
            "bContributeToMass": true
          },
          {
            "VertexData": [
              {
                "X": 568.3077,
                "Y": 256.4633,
                "Z": 3.8467255
              },
              {
                "X": 337.7187,
                "Y": 350.57217,
                "Z": 3.8467102
              },
              {
                "X": 337.7187,
                "Y": -12.361816,
                "Z": 3.846756
              },
              {
                "X": 478.0683,
                "Y": -12.361816,
                "Z": 3.846756
              },
              {
                "X": 478.0683,
                "Y": 350.57217,
                "Z": 3.8467102
              },
              {
                "X": 568.3077,
                "Y": 81.7471,
                "Z": 3.8467407
              },
              {
                "X": 568.3077,
                "Y": 256.46313,
                "Z": -1024.8474
              },
              {
                "X": 337.7187,
                "Y": 350.57202,
                "Z": -1024.8474
              },
              {
                "X": 337.7187,
                "Y": -12.361938,
                "Z": -1024.8474
              },
              {
                "X": 478.0683,
                "Y": -12.361938,
                "Z": -1024.8474
              },
              {
                "X": 478.0683,
                "Y": 350.57202,
                "Z": -1024.8474
              },
              {
                "X": 568.3077,
                "Y": 81.74695,
                "Z": -1024.8474
              }
            ],
            "ElemBox": {
              "Min": {
                "X": 337.7187,
                "Y": -12.361938,
                "Z": -1024.8474
              },
              "Max": {
                "X": 568.3077,
                "Y": 350.57217,
                "Z": 3.846756
              },
              "IsValid": 1
            },
            "Transform": {
              "Rotation": {
                "X": 0.0,
                "Y": 0.0,
                "Z": 0.0,
                "W": 1.0,
                "SizeSquared": 1.0,
                "Size": 1.0,
                "IsNormalized": true
              },
              "Translation": {
                "X": 0.0,
                "Y": 0.0,
                "Z": 0.0
              },
              "Scale3D": {
                "X": 1.0,
                "Y": 1.0,
                "Z": 1.0
              }
            },
            "RestOffset": 0.0,
            "Name": "None",
            "bContributeToMass": true
          },
          {
            "VertexData": [
              {
                "X": -379.04865,
                "Y": 842.6282,
                "Z": 9.626845E-14
              },
              {
                "X": -311.1043,
                "Y": 842.6282,
                "Z": 9.626845E-14
              },
              {
                "X": -379.04865,
                "Y": 346.88635,
                "Z": 1.2662389E-13
              },
              {
                "X": -311.1043,
                "Y": 346.88635,
                "Z": 1.2662389E-13
              },
              {
                "X": -379.04865,
                "Y": 842.6282,
                "Z": 49.14638
              },
              {
                "X": -311.1043,
                "Y": 842.6282,
                "Z": 49.14638
              },
              {
                "X": -379.04865,
                "Y": 346.88635,
                "Z": 49.14638
              },
              {
                "X": -311.1043,
                "Y": 346.88635,
                "Z": 49.14638
              }
            ],
            "ElemBox": {
              "Min": {
                "X": -379.04865,
                "Y": 346.88635,
                "Z": 9.626845E-14
              },
              "Max": {
                "X": -311.1043,
                "Y": 842.6282,
                "Z": 49.14638
              },
              "IsValid": 1
            },
            "Transform": {
              "Rotation": {
                "X": 0.0,
                "Y": 0.0,
                "Z": 0.0,
                "W": 1.0,
                "SizeSquared": 1.0,
                "Size": 1.0,
                "IsNormalized": true
              },
              "Translation": {
                "X": 0.0,
                "Y": 0.0,
                "Z": 0.0
              },
              "Scale3D": {
                "X": 1.0,
                "Y": 1.0,
                "Z": 1.0
              }
            },
            "RestOffset": 0.0,
            "Name": "None",
            "bContributeToMass": true
          },
          {
            "VertexData": [
              {
                "X": -377.7599,
                "Y": 1320.1516,
                "Z": -129.08118
              },
              {
                "X": -309.81555,
                "Y": 1320.1516,
                "Z": -129.08118
              },
              {
                "X": -377.7599,
                "Y": 841.30176,
                "Z": -0.77376556
              },
              {
                "X": -309.81555,
                "Y": 841.30176,
                "Z": -0.77376556
              },
              {
                "X": -377.7599,
                "Y": 1332.8716,
                "Z": -63.142693
              },
              {
                "X": -309.81555,
                "Y": 1332.8716,
                "Z": -63.142693
              },
              {
                "X": -377.7599,
                "Y": 840.69916,
                "Z": 49.62816
              },
              {
                "X": -309.81555,
                "Y": 840.69916,
                "Z": 49.62816
              }
            ],
            "ElemBox": {
              "Min": {
                "X": -377.7599,
                "Y": 840.69916,
                "Z": -129.08118
              },
              "Max": {
                "X": -309.81555,
                "Y": 1332.8716,
                "Z": 49.62816
              },
              "IsValid": 1
            },
            "Transform": {
              "Rotation": {
                "X": 0.0,
                "Y": 0.0,
                "Z": 0.0,
                "W": 1.0,
                "SizeSquared": 1.0,
                "Size": 1.0,
                "IsNormalized": true
              },
              "Translation": {
                "X": 0.0,
                "Y": 0.0,
                "Z": 0.0
              },
              "Scale3D": {
                "X": 1.0,
                "Y": 1.0,
                "Z": 1.0
              }
            },
            "RestOffset": 0.0,
            "Name": "None",
            "bContributeToMass": true
          },
          {
            "VertexData": [
              {
                "X": 377.7599,
                "Y": 1320.1516,
                "Z": -129.0813
              },
              {
                "X": 309.81555,
                "Y": 1320.1516,
                "Z": -129.0813
              },
              {
                "X": 377.7599,
                "Y": 841.30176,
                "Z": -0.77384186
              },
              {
                "X": 309.81555,
                "Y": 841.30176,
                "Z": -0.77384186
              },
              {
                "X": 377.7599,
                "Y": 1332.8716,
                "Z": -63.142815
              },
              {
                "X": 309.81555,
                "Y": 1332.8716,
                "Z": -63.142815
              },
              {
                "X": 377.7599,
                "Y": 840.69916,
                "Z": 49.62809
              },
              {
                "X": 309.81555,
                "Y": 840.69916,
                "Z": 49.62809
              }
            ],
            "ElemBox": {
              "Min": {
                "X": 309.81555,
                "Y": 840.69916,
                "Z": -129.0813
              },
              "Max": {
                "X": 377.7599,
                "Y": 1332.8716,
                "Z": 49.62809
              },
              "IsValid": 1
            },
            "Transform": {
              "Rotation": {
                "X": 0.0,
                "Y": 0.0,
                "Z": 0.0,
                "W": 1.0,
                "SizeSquared": 1.0,
                "Size": 1.0,
                "IsNormalized": true
              },
              "Translation": {
                "X": 0.0,
                "Y": 0.0,
                "Z": 0.0
              },
              "Scale3D": {
                "X": 1.0,
                "Y": 1.0,
                "Z": 1.0
              }
            },
            "RestOffset": 0.0,
            "Name": "None",
            "bContributeToMass": true
          },
          {
            "VertexData": [
              {
                "X": 379.04865,
                "Y": 842.6282,
                "Z": -9.06029E-05
              },
              {
                "X": 311.1043,
                "Y": 842.6282,
                "Z": -9.06029E-05
              },
              {
                "X": 379.04865,
                "Y": 346.88635,
                "Z": -1.5747977E-05
              },
              {
                "X": 311.1043,
                "Y": 346.88635,
                "Z": -1.5747977E-05
              },
              {
                "X": 379.04865,
                "Y": 842.6282,
                "Z": 49.14629
              },
              {
                "X": 311.1043,
                "Y": 842.6282,
                "Z": 49.14629
              },
              {
                "X": 379.04865,
                "Y": 346.88635,
                "Z": 49.146366
              },
              {
                "X": 311.1043,
                "Y": 346.88635,
                "Z": 49.146366
              }
            ],
            "ElemBox": {
              "Min": {
                "X": 311.1043,
                "Y": 346.88635,
                "Z": -9.06029E-05
              },
              "Max": {
                "X": 379.04865,
                "Y": 842.6282,
                "Z": 49.146366
              },
              "IsValid": 1
            },
            "Transform": {
              "Rotation": {
                "X": 0.0,
                "Y": 0.0,
                "Z": 0.0,
                "W": 1.0,
                "SizeSquared": 1.0,
                "Size": 1.0,
                "IsNormalized": true
              },
              "Translation": {
                "X": 0.0,
                "Y": 0.0,
                "Z": 0.0
              },
              "Scale3D": {
                "X": 1.0,
                "Y": 1.0,
                "Z": 1.0
              }
            },
            "RestOffset": 0.0,
            "Name": "None",
            "bContributeToMass": true
          },
          {
            "VertexData": [
              {
                "X": -273.07507,
                "Y": -16.483429,
                "Z": 8.038518E-14
              },
              {
                "X": -273.07504,
                "Y": 46.427948,
                "Z": 7.653297E-14
              },
              {
                "X": -448.12576,
                "Y": 46.42801,
                "Z": 7.653297E-14
              },
              {
                "X": -467.53128,
                "Y": -16.483368,
                "Z": 8.038518E-14
              },
              {
                "X": -273.07507,
                "Y": -16.483429,
                "Z": 81.53317
              },
              {
                "X": -467.53128,
                "Y": -16.483368,
                "Z": 81.53317
              },
              {
                "X": -448.12576,
                "Y": 46.42801,
                "Z": 81.53317
              },
              {
                "X": -273.07504,
                "Y": 46.427948,
                "Z": 81.53317
              }
            ],
            "ElemBox": {
              "Min": {
                "X": -467.53128,
                "Y": -16.483429,
                "Z": 7.653297E-14
              },
              "Max": {
                "X": -273.07504,
                "Y": 46.42801,
                "Z": 81.53317
              },
              "IsValid": 1
            },
            "Transform": {
              "Rotation": {
                "X": 0.0,
                "Y": 0.0,
                "Z": 0.0,
                "W": 1.0,
                "SizeSquared": 1.0,
                "Size": 1.0,
                "IsNormalized": true
              },
              "Translation": {
                "X": -27.422272,
                "Y": 0.0,
                "Z": 6.1035156E-05
              },
              "Scale3D": {
                "X": 1.0,
                "Y": 1.0,
                "Z": 1.0
              }
            },
            "RestOffset": 0.0,
            "Name": "None",
            "bContributeToMass": true
          },
          {
            "VertexData": [
              {
                "X": -470.4346,
                "Y": -21.066742,
                "Z": 8.066583E-14
              },
              {
                "X": -425.94952,
                "Y": 23.418304,
                "Z": 7.7941905E-14
              },
              {
                "X": -549.729,
                "Y": 147.19786,
                "Z": 7.036259E-14
              },
              {
                "X": -594.2141,
                "Y": 102.7128,
                "Z": 7.3086516E-14
              },
              {
                "X": -470.4346,
                "Y": -21.066742,
                "Z": 81.53317
              },
              {
                "X": -594.2141,
                "Y": 102.7128,
                "Z": 81.53317
              },
              {
                "X": -549.729,
                "Y": 147.19786,
                "Z": 81.53317
              },
              {
                "X": -425.94952,
                "Y": 23.418304,
                "Z": 81.53317
              }
            ],
            "ElemBox": {
              "Min": {
                "X": -594.2141,
                "Y": -21.066742,
                "Z": 7.036259E-14
              },
              "Max": {
                "X": -425.94952,
                "Y": 147.19786,
                "Z": 81.53317
              },
              "IsValid": 1
            },
            "Transform": {
              "Rotation": {
                "X": 0.0,
                "Y": 0.0,
                "Z": 0.0,
                "W": 1.0,
                "SizeSquared": 1.0,
                "Size": 1.0,
                "IsNormalized": true
              },
              "Translation": {
                "X": 0.0,
                "Y": 0.0,
                "Z": 0.0
              },
              "Scale3D": {
                "X": 1.0,
                "Y": 1.0,
                "Z": 1.0
              }
            },
            "RestOffset": 0.0,
            "Name": "None",
            "bContributeToMass": true
          },
          {
            "VertexData": [
              {
                "X": -588.5465,
                "Y": 79.578125,
                "Z": 7.450311E-14
              },
              {
                "X": -525.63513,
                "Y": 79.578125,
                "Z": 7.450311E-14
              },
              {
                "X": -525.63513,
                "Y": 254.6288,
                "Z": 6.3784346E-14
              },
              {
                "X": -588.5465,
                "Y": 254.62881,
                "Z": 6.3784346E-14
              },
              {
                "X": -588.5465,
                "Y": 79.578125,
                "Z": 81.53317
              },
              {
                "X": -588.5465,
                "Y": 254.62881,
                "Z": 81.53317
              },
              {
                "X": -525.63513,
                "Y": 254.6288,
                "Z": 81.53317
              },
              {
                "X": -525.63513,
                "Y": 79.578125,
                "Z": 81.53317
              }
            ],
            "ElemBox": {
              "Min": {
                "X": -588.5465,
                "Y": 79.578125,
                "Z": 6.3784346E-14
              },
              "Max": {
                "X": -525.63513,
                "Y": 254.62881,
                "Z": 81.53317
              },
              "IsValid": 1
            },
            "Transform": {
              "Rotation": {
                "X": 0.0,
                "Y": 0.0,
                "Z": 0.0,
                "W": 1.0,
                "SizeSquared": 1.0,
                "Size": 1.0,
                "IsNormalized": true
              },
              "Translation": {
                "X": 0.0,
                "Y": 0.0,
                "Z": 0.0
              },
              "Scale3D": {
                "X": 1.0,
                "Y": 1.0,
                "Z": 1.0
              }
            },
            "RestOffset": 0.0,
            "Name": "None",
            "bContributeToMass": true
          },
          {
            "VertexData": [
              {
                "X": -591.7635,
                "Y": 254.30078,
                "Z": 6.380443E-14
              },
              {
                "X": -558.6754,
                "Y": 194.37491,
                "Z": 6.747383E-14
              },
              {
                "X": -424.57883,
                "Y": 306.8953,
                "Z": 6.058395E-14
              },
              {
                "X": -465.0175,
                "Y": 355.08826,
                "Z": 5.763298E-14
              },
              {
                "X": -591.7635,
                "Y": 254.30078,
                "Z": 81.53317
              },
              {
                "X": -465.0175,
                "Y": 355.08826,
                "Z": 81.53317
              },
              {
                "X": -424.57883,
                "Y": 306.8953,
                "Z": 81.53317
              },
              {
                "X": -558.6754,
                "Y": 194.37491,
                "Z": 81.53317
              }
            ],
            "ElemBox": {
              "Min": {
                "X": -591.7635,
                "Y": 194.37491,
                "Z": 5.763298E-14
              },
              "Max": {
                "X": -424.57883,
                "Y": 355.08826,
                "Z": 81.53317
              },
              "IsValid": 1
            },
            "Transform": {
              "Rotation": {
                "X": 0.0,
                "Y": 0.0,
                "Z": 0.0,
                "W": 1.0,
                "SizeSquared": 1.0,
                "Size": 1.0,
                "IsNormalized": true
              },
              "Translation": {
                "X": 0.0,
                "Y": 0.0,
                "Z": 0.0
              },
              "Scale3D": {
                "X": 1.0,
                "Y": 1.0,
                "Z": 1.0
              }
            },
            "RestOffset": 0.0,
            "Name": "None",
            "bContributeToMass": true
          },
          {
            "VertexData": [
              {
                "X": -465.326,
                "Y": 350.73016,
                "Z": 5.789984E-14
              },
              {
                "X": -273.2915,
                "Y": 350.73016,
                "Z": 5.789984E-14
              },
              {
                "X": -448.34216,
                "Y": 287.81873,
                "Z": 6.175205E-14
              },
              {
                "X": -273.2915,
                "Y": 287.81873,
                "Z": 6.175205E-14
              },
              {
                "X": -465.326,
                "Y": 350.73016,
                "Z": 81.53317
              },
              {
                "X": -273.2915,
                "Y": 350.73016,
                "Z": 81.53317
              },
              {
                "X": -448.34216,
                "Y": 287.81873,
                "Z": 81.53317
              },
              {
                "X": -273.2915,
                "Y": 287.81873,
                "Z": 81.53317
              }
            ],
            "ElemBox": {
              "Min": {
                "X": -465.326,
                "Y": 287.81873,
                "Z": 5.789984E-14
              },
              "Max": {
                "X": -273.2915,
                "Y": 350.73016,
                "Z": 81.53317
              },
              "IsValid": 1
            },
            "Transform": {
              "Rotation": {
                "X": 0.0,
                "Y": 0.0,
                "Z": 0.0,
                "W": 1.0,
                "SizeSquared": 1.0,
                "Size": 1.0,
                "IsNormalized": true
              },
              "Translation": {
                "X": -34.62979,
                "Y": 0.0,
                "Z": 0.0
              },
              "Scale3D": {
                "X": 1.0,
                "Y": 1.0,
                "Z": 1.0
              }
            },
            "RestOffset": 0.0,
            "Name": "None",
            "bContributeToMass": true
          },
          {
            "VertexData": [
              {
                "X": -375.77905,
                "Y": -10.076263,
                "Z": -1014.4783
              },
              {
                "X": -304.06006,
                "Y": -10.076263,
                "Z": -1014.4783
              },
              {
                "X": -375.77905,
                "Y": -137.15729,
                "Z": -1014.4783
              },
              {
                "X": -304.06006,
                "Y": -137.15729,
                "Z": -1014.4783
              },
              {
                "X": -375.77905,
                "Y": -10.076263,
                "Z": 22.542664
              },
              {
                "X": -304.06006,
                "Y": -10.076263,
                "Z": 22.542664
              },
              {
                "X": -375.77905,
                "Y": -137.15729,
                "Z": 22.542664
              },
              {
                "X": -304.06006,
                "Y": -137.15729,
                "Z": 22.542664
              }
            ],
            "ElemBox": {
              "Min": {
                "X": -375.77905,
                "Y": -137.15729,
                "Z": -1014.4783
              },
              "Max": {
                "X": -304.06006,
                "Y": -10.076263,
                "Z": 22.542664
              },
              "IsValid": 1
            },
            "Transform": {
              "Rotation": {
                "X": 0.0,
                "Y": 0.0,
                "Z": 0.0,
                "W": 1.0,
                "SizeSquared": 1.0,
                "Size": 1.0,
                "IsNormalized": true
              },
              "Translation": {
                "X": 0.0,
                "Y": 0.0,
                "Z": 0.0
              },
              "Scale3D": {
                "X": 1.0,
                "Y": 1.0,
                "Z": 1.0
              }
            },
            "RestOffset": 0.0,
            "Name": "None",
            "bContributeToMass": true
          },
          {
            "VertexData": [
              {
                "X": 375.77905,
                "Y": -10.076263,
                "Z": -1014.4783
              },
              {
                "X": 375.77905,
                "Y": -137.15729,
                "Z": -1014.4783
              },
              {
                "X": 304.06006,
                "Y": -137.15729,
                "Z": -1014.4783
              },
              {
                "X": 304.06006,
                "Y": -10.076263,
                "Z": -1014.4783
              },
              {
                "X": 375.77905,
                "Y": -10.076263,
                "Z": 22.542664
              },
              {
                "X": 304.06006,
                "Y": -10.076263,
                "Z": 22.542664
              },
              {
                "X": 304.06006,
                "Y": -137.15729,
                "Z": 22.542664
              },
              {
                "X": 375.77905,
                "Y": -137.15729,
                "Z": 22.542664
              }
            ],
            "ElemBox": {
              "Min": {
                "X": 304.06006,
                "Y": -137.15729,
                "Z": -1014.4783
              },
              "Max": {
                "X": 375.77905,
                "Y": -10.076263,
                "Z": 22.542664
              },
              "IsValid": 1
            },
            "Transform": {
              "Rotation": {
                "X": 0.0,
                "Y": 0.0,
                "Z": 0.0,
                "W": 1.0,
                "SizeSquared": 1.0,
                "Size": 1.0,
                "IsNormalized": true
              },
              "Translation": {
                "X": 0.0,
                "Y": 0.0,
                "Z": 0.0
              },
              "Scale3D": {
                "X": 1.0,
                "Y": 1.0,
                "Z": 1.0
              }
            },
            "RestOffset": 0.0,
            "Name": "None",
            "bContributeToMass": true
          },
          {
            "VertexData": [
              {
                "X": 465.326,
                "Y": 350.73016,
                "Z": 3.0661806E-05
              },
              {
                "X": 273.2915,
                "Y": 350.73016,
                "Z": 3.0661806E-05
              },
              {
                "X": 448.34216,
                "Y": 287.81873,
                "Z": 2.5161911E-05
              },
              {
                "X": 273.2915,
                "Y": 287.81873,
                "Z": 2.5161911E-05
              },
              {
                "X": 465.326,
                "Y": 350.73016,
                "Z": 81.5332
              },
              {
                "X": 273.2915,
                "Y": 350.73016,
                "Z": 81.5332
              },
              {
                "X": 448.34216,
                "Y": 287.81873,
                "Z": 81.533195
              },
              {
                "X": 273.2915,
                "Y": 287.81873,
                "Z": 81.533195
              }
            ],
            "ElemBox": {
              "Min": {
                "X": 273.2915,
                "Y": 287.81873,
                "Z": 2.5161911E-05
              },
              "Max": {
                "X": 465.326,
                "Y": 350.73016,
                "Z": 81.5332
              },
              "IsValid": 1
            },
            "Transform": {
              "Rotation": {
                "X": 0.0,
                "Y": 0.0,
                "Z": 0.0,
                "W": 1.0,
                "SizeSquared": 1.0,
                "Size": 1.0,
                "IsNormalized": true
              },
              "Translation": {
                "X": 33.814865,
                "Y": 0.0,
                "Z": 0.0
              },
              "Scale3D": {
                "X": 1.0,
                "Y": 1.0,
                "Z": 1.0
              }
            },
            "RestOffset": 0.0,
            "Name": "None",
            "bContributeToMass": true
          },
          {
            "VertexData": [
              {
                "X": 591.7635,
                "Y": 254.30078,
                "Z": 2.2231681E-05
              },
              {
                "X": 558.6754,
                "Y": 194.37491,
                "Z": 1.6992793E-05
              },
              {
                "X": 424.57883,
                "Y": 306.8953,
                "Z": 2.6829639E-05
              },
              {
                "X": 465.0175,
                "Y": 355.08826,
                "Z": 3.10428E-05
              },
              {
                "X": 591.7635,
                "Y": 254.30078,
                "Z": 81.533195
              },
              {
                "X": 465.0175,
                "Y": 355.08826,
                "Z": 81.5332
              },
              {
                "X": 424.57883,
                "Y": 306.8953,
                "Z": 81.5332
              },
              {
                "X": 558.6754,
                "Y": 194.37491,
                "Z": 81.53319
              }
            ],
            "ElemBox": {
              "Min": {
                "X": 424.57883,
                "Y": 194.37491,
                "Z": 1.6992793E-05
              },
              "Max": {
                "X": 591.7635,
                "Y": 355.08826,
                "Z": 81.5332
              },
              "IsValid": 1
            },
            "Transform": {
              "Rotation": {
                "X": 0.0,
                "Y": 0.0,
                "Z": 0.0,
                "W": 1.0,
                "SizeSquared": 1.0,
                "Size": 1.0,
                "IsNormalized": true
              },
              "Translation": {
                "X": 0.0,
                "Y": 0.0,
                "Z": 0.0
              },
              "Scale3D": {
                "X": 1.0,
                "Y": 1.0,
                "Z": 1.0
              }
            },
            "RestOffset": 0.0,
            "Name": "None",
            "bContributeToMass": true
          },
          {
            "VertexData": [
              {
                "X": 588.5465,
                "Y": 79.578125,
                "Z": 6.9569405E-06
              },
              {
                "X": 525.63513,
                "Y": 79.578125,
                "Z": 6.9569405E-06
              },
              {
                "X": 525.63513,
                "Y": 254.6288,
                "Z": 2.2260356E-05
              },
              {
                "X": 588.5465,
                "Y": 254.62881,
                "Z": 2.2260358E-05
              },
              {
                "X": 588.5465,
                "Y": 79.57812,
                "Z": 81.53318
              },
              {
                "X": 588.5465,
                "Y": 254.62881,
                "Z": 81.533195
              },
              {
                "X": 525.63513,
                "Y": 254.6288,
                "Z": 81.533195
              },
              {
                "X": 525.63513,
                "Y": 79.57812,
                "Z": 81.53318
              }
            ],
            "ElemBox": {
              "Min": {
                "X": 525.63513,
                "Y": 79.57812,
                "Z": 6.9569405E-06
              },
              "Max": {
                "X": 588.5465,
                "Y": 254.62881,
                "Z": 81.533195
              },
              "IsValid": 1
            },
            "Transform": {
              "Rotation": {
                "X": 0.0,
                "Y": 0.0,
                "Z": 0.0,
                "W": 1.0,
                "SizeSquared": 1.0,
                "Size": 1.0,
                "IsNormalized": true
              },
              "Translation": {
                "X": 0.0,
                "Y": 0.0,
                "Z": 0.0
              },
              "Scale3D": {
                "X": 1.0,
                "Y": 1.0,
                "Z": 1.0
              }
            },
            "RestOffset": 0.0,
            "Name": "None",
            "bContributeToMass": true
          },
          {
            "VertexData": [
              {
                "X": 470.4346,
                "Y": -21.066742,
                "Z": -1.841713E-06
              },
              {
                "X": 425.94952,
                "Y": 23.418304,
                "Z": 2.0472933E-06
              },
              {
                "X": 549.729,
                "Y": 147.19786,
                "Z": 1.2868446E-05
              },
              {
                "X": 594.2141,
                "Y": 102.7128,
                "Z": 8.9794385E-06
              },
              {
                "X": 470.4346,
                "Y": -21.06675,
                "Z": 81.53317
              },
              {
                "X": 594.2141,
                "Y": 102.71279,
                "Z": 81.53318
              },
              {
                "X": 549.729,
                "Y": 147.19786,
                "Z": 81.53319
              },
              {
                "X": 425.94952,
                "Y": 23.418297,
                "Z": 81.53317
              }
            ],
            "ElemBox": {
              "Min": {
                "X": 425.94952,
                "Y": -21.06675,
                "Z": -1.841713E-06
              },
              "Max": {
                "X": 594.2141,
                "Y": 147.19786,
                "Z": 81.53319
              },
              "IsValid": 1
            },
            "Transform": {
              "Rotation": {
                "X": 0.0,
                "Y": 0.0,
                "Z": 0.0,
                "W": 1.0,
                "SizeSquared": 1.0,
                "Size": 1.0,
                "IsNormalized": true
              },
              "Translation": {
                "X": 0.0,
                "Y": 0.0,
                "Z": 0.0
              },
              "Scale3D": {
                "X": 1.0,
                "Y": 1.0,
                "Z": 1.0
              }
            },
            "RestOffset": 0.0,
            "Name": "None",
            "bContributeToMass": true
          },
          {
            "VertexData": [
              {
                "X": 273.07507,
                "Y": -16.483429,
                "Z": -1.441027E-06
              },
              {
                "X": 273.07504,
                "Y": 46.427948,
                "Z": 4.05886E-06
              },
              {
                "X": 448.12576,
                "Y": 46.42801,
                "Z": 4.0588657E-06
              },
              {
                "X": 467.53128,
                "Y": -16.483368,
                "Z": -1.4410217E-06
              },
              {
                "X": 273.07507,
                "Y": -16.483437,
                "Z": 81.53317
              },
              {
                "X": 467.53128,
                "Y": -16.483376,
                "Z": 81.53317
              },
              {
                "X": 448.12576,
                "Y": 46.428,
                "Z": 81.53318
              },
              {
                "X": 273.07504,
                "Y": 46.42794,
                "Z": 81.53318
              }
            ],
            "ElemBox": {
              "Min": {
                "X": 273.07504,
                "Y": -16.483437,
                "Z": -1.441027E-06
              },
              "Max": {
                "X": 467.53128,
                "Y": 46.42801,
                "Z": 81.53318
              },
              "IsValid": 1
            },
            "Transform": {
              "Rotation": {
                "X": 0.0,
                "Y": 0.0,
                "Z": 0.0,
                "W": 1.0,
                "SizeSquared": 1.0,
                "Size": 1.0,
                "IsNormalized": true
              },
              "Translation": {
                "X": 30.418777,
                "Y": 0.0,
                "Z": 0.0
              },
              "Scale3D": {
                "X": 1.0,
                "Y": 1.0,
                "Z": 1.0
              }
            },
            "RestOffset": 0.0,
            "Name": "None",
            "bContributeToMass": true
          },
          {
            "VertexData": [
              {
                "X": -376.63336,
                "Y": 127.68336,
                "Z": 173.43549
              },
              {
                "X": -376.63336,
                "Y": 144.80042,
                "Z": -0.16788864
              },
              {
                "X": -376.63336,
                "Y": 72.42751,
                "Z": -0.16788864
              },
              {
                "X": -376.63336,
                "Y": 72.42751,
                "Z": 157.02222
              },
              {
                "X": -376.63336,
                "Y": 144.80042,
                "Z": 157.02222
              },
              {
                "X": -376.63336,
                "Y": 89.544586,
                "Z": 173.43549
              },
              {
                "X": -414.854,
                "Y": 127.68336,
                "Z": 173.43549
              },
              {
                "X": -414.854,
                "Y": 144.80042,
                "Z": -0.16788864
              },
              {
                "X": -414.854,
                "Y": 72.42751,
                "Z": -0.16788864
              },
              {
                "X": -414.85394,
                "Y": 72.42751,
                "Z": 157.02222
              },
              {
                "X": -414.85394,
                "Y": 144.80042,
                "Z": 157.02222
              },
              {
                "X": -414.854,
                "Y": 89.544586,
                "Z": 173.43549
              }
            ],
            "ElemBox": {
              "Min": {
                "X": -414.854,
                "Y": 72.42751,
                "Z": -0.16788864
              },
              "Max": {
                "X": -376.63336,
                "Y": 144.80042,
                "Z": 173.43549
              },
              "IsValid": 1
            },
            "Transform": {
              "Rotation": {
                "X": 0.0,
                "Y": 0.0,
                "Z": 0.0,
                "W": 1.0,
                "SizeSquared": 1.0,
                "Size": 1.0,
                "IsNormalized": true
              },
              "Translation": {
                "X": 0.0,
                "Y": 0.0,
                "Z": 0.0
              },
              "Scale3D": {
                "X": 1.0,
                "Y": 1.0,
                "Z": 1.0
              }
            },
            "RestOffset": 0.0,
            "Name": "None",
            "bContributeToMass": true
          },
          {
            "VertexData": [
              {
                "X": 312.43018,
                "Y": 184.25307,
                "Z": -6.734123
              },
              {
                "X": 312.43018,
                "Y": 162.87106,
                "Z": -2.1107755
              },
              {
                "X": 312.43018,
                "Y": 138.5464,
                "Z": 2.0600052
              },
              {
                "X": 312.43018,
                "Y": 100.65985,
                "Z": 5.369954
              },
              {
                "X": 312.43018,
                "Y": 52.920013,
                "Z": 7.495076
              },
              {
                "X": 312.43018,
                "Y": 5.1259995E-06,
                "Z": 8.227343
              },
              {
                "X": 312.43018,
                "Y": -52.92,
                "Z": 7.4950733
              },
              {
                "X": 312.4302,
                "Y": -100.65983,
                "Z": 5.369954
              },
              {
                "X": 312.43018,
                "Y": -138.54637,
                "Z": 2.0600052
              },
              {
                "X": 312.43018,
                "Y": -162.87102,
                "Z": -2.1107755
              },
              {
                "X": 312.4302,
                "Y": -184.25304,
                "Z": -6.734127
              },
              {
                "X": -312.4302,
                "Y": 184.25307,
                "Z": -6.734127
              },
              {
                "X": -312.43018,
                "Y": 162.87106,
                "Z": -2.110779
              },
              {
                "X": -312.43018,
                "Y": 138.5464,
                "Z": 2.0600014
              },
              {
                "X": -312.4302,
                "Y": 100.65985,
                "Z": 5.3699503
              },
              {
                "X": -312.43018,
                "Y": 52.920013,
                "Z": 7.4950733
              },
              {
                "X": -312.43018,
                "Y": 5.1259995E-06,
                "Z": 8.22734
              },
              {
                "X": -312.43018,
                "Y": -52.92,
                "Z": 7.4950695
              },
              {
                "X": -312.43018,
                "Y": -100.65983,
                "Z": 5.3699503
              },
              {
                "X": -312.43018,
                "Y": -138.54637,
                "Z": 2.0600052
              },
              {
                "X": -312.43018,
                "Y": -162.87102,
                "Z": -2.1107755
              },
              {
                "X": -312.43018,
                "Y": -184.25304,
                "Z": -6.734123
              },
              {
                "X": 312.43018,
                "Y": 9.923965E-24,
                "Z": -6.734123
              },
              {
                "X": -312.43018,
                "Y": 9.923965E-24,
                "Z": -6.734123
              }
            ],
            "ElemBox": {
              "Min": {
                "X": -312.4302,
                "Y": -184.25304,
                "Z": -6.734127
              },
              "Max": {
                "X": 312.4302,
                "Y": 184.25307,
                "Z": 8.227343
              },
              "IsValid": 1
            },
            "Transform": {
              "Rotation": {
                "X": 0.0,
                "Y": 0.0,
                "Z": 0.0,
                "W": 1.0,
                "SizeSquared": 1.0,
                "Size": 1.0,
                "IsNormalized": true
              },
              "Translation": {
                "X": 0.0,
                "Y": 0.0,
                "Z": 0.0
              },
              "Scale3D": {
                "X": 1.0,
                "Y": 1.0,
                "Z": 1.0
              }
            },
            "RestOffset": 0.0,
            "Name": "None",
            "bContributeToMass": true
          },
          {
            "VertexData": [
              {
                "X": -314.5937,
                "Y": 1283.5216,
                "Z": -124.14627
              },
              {
                "X": 314.5937,
                "Y": 1283.5216,
                "Z": -124.14627
              },
              {
                "X": -314.5937,
                "Y": -2.1324754,
                "Z": -3.332973
              },
              {
                "X": 314.5937,
                "Y": -2.1324754,
                "Z": -3.332973
              },
              {
                "X": -314.5937,
                "Y": -2.1324754,
                "Z": -191.00616
              },
              {
                "X": 314.5937,
                "Y": -2.1324754,
                "Z": -191.00616
              },
              {
                "X": -314.5937,
                "Y": 1359.0887,
                "Z": -162.02275
              },
              {
                "X": 314.5937,
                "Y": 1359.0887,
                "Z": -162.02275
              },
              {
                "X": 314.5937,
                "Y": 832.6854,
                "Z": -191.00616
              },
              {
                "X": -314.5937,
                "Y": 832.6854,
                "Z": -191.00616
              },
              {
                "X": -314.5937,
                "Y": 900.4456,
                "Z": -18.030668
              },
              {
                "X": -314.5937,
                "Y": 866.60034,
                "Z": -11.621134
              },
              {
                "X": -314.5937,
                "Y": 832.311,
                "Z": -7.023186
              },
              {
                "X": -314.5937,
                "Y": 797.7249,
                "Z": -4.2565155
              },
              {
                "X": -314.5937,
                "Y": 762.99,
                "Z": -3.332973
              },
              {
                "X": 314.5937,
                "Y": 762.99,
                "Z": -3.332973
              },
              {
                "X": 314.5937,
                "Y": 797.7249,
                "Z": -4.2565155
              },
              {
                "X": 314.5937,
                "Y": 832.311,
                "Z": -7.023186
              },
              {
                "X": 314.5937,
                "Y": 866.60034,
                "Z": -11.621134
              },
              {
                "X": 314.5937,
                "Y": 900.4456,
                "Z": -18.030668
              },
              {
                "X": -314.5937,
                "Y": -2.1324754,
                "Z": -1014.3799
              },
              {
                "X": 314.5937,
                "Y": -2.1324754,
                "Z": -1014.3799
              },
              {
                "X": 314.5937,
                "Y": 832.6854,
                "Z": -1014.3799
              },
              {
                "X": -314.5937,
                "Y": 832.6854,
                "Z": -1014.3799
              },
              {
                "X": 314.5937,
                "Y": 1359.0887,
                "Z": -1014.3799
              },
              {
                "X": -314.5937,
                "Y": 1359.0887,
                "Z": -1014.3799
              }
            ],
            "ElemBox": {
              "Min": {
                "X": -314.5937,
                "Y": -2.1324754,
                "Z": -1014.3799
              },
              "Max": {
                "X": 314.5937,
                "Y": 1359.0887,
                "Z": -3.332973
              },
              "IsValid": 1
            },
            "Transform": {
              "Rotation": {
                "X": 0.0,
                "Y": 0.0,
                "Z": 0.0,
                "W": 1.0,
                "SizeSquared": 1.0,
                "Size": 1.0,
                "IsNormalized": true
              },
              "Translation": {
                "X": 0.0,
                "Y": 0.0,
                "Z": 0.0
              },
              "Scale3D": {
                "X": 1.0,
                "Y": 1.0,
                "Z": 1.0
              }
            },
            "RestOffset": 0.0,
            "Name": "None",
            "bContributeToMass": true
          }
        ]
      },
      "BoneName": "root",
      "CollisionTraceFlag": "CTF_UseSimpleAsComplex"
    }
  }
]