[
  {
    "Type": "BodySetup",
    "Name": "BodySetup_1",
    "Outer": "CanalWall1a",
    "Properties": {
      "AggGeom": {
        "ConvexElems": [
          {
            "VertexData": [
              {
                "X": 336.56085,
                "Y": -314.84268,
                "Z": -480.43655
              },
              {
                "X": 375.38483,
                "Y": -408.5721,
                "Z": -480.43658
              },
              {
                "X": 375.38483,
                "Y": -408.5722,
                "Z": -8.620157E-05
              },
              {
                "X": 336.56085,
                "Y": -314.84274,
                "Z": -7.0931106E-05
              },
              {
                "X": 637.3322,
                "Y": -141.19229,
                "Z": -480.4365
              },
              {
                "X": 710.8517,
                "Y": -318.68408,
                "Z": -480.43652
              },
              {
                "X": 604.9104,
                "Y": -347.071,
                "Z": -7.5900745E-05
              },
              {
                "X": 542.34784,
                "Y": -196.0316,
                "Z": -5.1355386E-05
              },
              {
                "X": 375.38483,
                "Y": -408.57202,
                "Z": -1120.9609
              },
              {
                "X": 710.8517,
                "Y": -318.684,
                "Z": -1120.9608
              },
              {
                "X": 336.56085,
                "Y": -314.84256,
                "Z": -1120.9609
              },
              {
                "X": 637.3322,
                "Y": -141.19218,
                "Z": -1120.9608
              }
            ],
            "ElemBox": {
              "Min": {
                "X": 336.56085,
                "Y": -408.5722,
                "Z": -1120.9609
              },
              "Max": {
                "X": 710.8517,
                "Y": -141.19218,
                "Z": -5.1355386E-05
              },
              "IsValid": 1
            },
            "Transform": {
              "Rotation": {
                "X": 0.0,
                "Y": 0.0,
                "Z": 0.0,
                "W": 1.0,
                "SizeSquared": 1.0,
                "Size": 1.0,
                "IsNormalized": true
              },
              "Translation": {
                "X": 0.0,
                "Y": 0.0,
                "Z": 0.0
              },
              "Scale3D": {
                "X": 1.0,
                "Y": 1.0,
                "Z": 1.0
              }
            },
            "RestOffset": 0.0,
            "Name": "None",
            "bContributeToMass": true
          },
          {
            "VertexData": [
              {
                "X": 274.80075,
                "Y": -234.3554,
                "Z": -480.43655
              },
              {
                "X": 336.56085,
                "Y": -314.84268,
                "Z": -480.43655
              },
              {
                "X": 336.56085,
                "Y": -314.84274,
                "Z": -7.0931106E-05
              },
              {
                "X": 274.80078,
                "Y": -234.3555,
                "Z": -5.7818066E-05
              },
              {
                "X": 520.3795,
                "Y": 11.223347,
                "Z": -480.43646
              },
              {
                "X": 637.3322,
                "Y": -141.19229,
                "Z": -480.4365
              },
              {
                "X": 542.34784,
                "Y": -196.0316,
                "Z": -5.1355386E-05
              },
              {
                "X": 442.82516,
                "Y": -66.33115,
                "Z": -3.0286588E-05
              },
              {
                "X": 274.80075,
                "Y": -234.35529,
                "Z": -1120.9609
              },
              {
                "X": 336.56085,
                "Y": -314.84256,
                "Z": -1120.9609
              },
              {
                "X": 520.3795,
                "Y": 11.223451,
                "Z": -1120.9608
              },
              {
                "X": 637.3322,
                "Y": -141.19218,
                "Z": -1120.9608
              }
            ],
            "ElemBox": {
              "Min": {
                "X": 274.80075,
                "Y": -314.84274,
                "Z": -1120.9609
              },
              "Max": {
                "X": 637.3322,
                "Y": 11.223451,
                "Z": -3.0286588E-05
              },
              "IsValid": 1
            },
            "Transform": {
              "Rotation": {
                "X": 0.0,
                "Y": 0.0,
                "Z": 0.0,
                "W": 1.0,
                "SizeSquared": 1.0,
                "Size": 1.0,
                "IsNormalized": true
              },
              "Translation": {
                "X": 0.0,
                "Y": 0.0,
                "Z": 0.0
              },
              "Scale3D": {
                "X": 1.0,
                "Y": 1.0,
                "Z": 1.0
              }
            },
            "RestOffset": 0.0,
            "Name": "None",
            "bContributeToMass": true
          },
          {
            "VertexData": [
              {
                "X": 194.31348,
                "Y": -172.59532,
                "Z": -480.43655
              },
              {
                "X": 274.80075,
                "Y": -234.3554,
                "Z": -480.43655
              },
              {
                "X": 274.80078,
                "Y": -234.3555,
                "Z": -5.7818066E-05
              },
              {
                "X": 194.31348,
                "Y": -172.5954,
                "Z": -4.775607E-05
              },
              {
                "X": 367.9639,
                "Y": 128.17601,
                "Z": -480.43646
              },
              {
                "X": 520.3795,
                "Y": 11.223347,
                "Z": -480.43646
              },
              {
                "X": 442.82516,
                "Y": -66.33115,
                "Z": -3.0286588E-05
              },
              {
                "X": 313.12466,
                "Y": 33.191586,
                "Z": -1.4134366E-05
              },
              {
                "X": 194.31348,
                "Y": -172.59523,
                "Z": -1120.9609
              },
              {
                "X": 274.80075,
                "Y": -234.35529,
                "Z": -1120.9609
              },
              {
                "X": 367.9639,
                "Y": 128.1761,
                "Z": -1120.9608
              },
              {
                "X": 520.3795,
                "Y": 11.223451,
                "Z": -1120.9608
              }
            ],
            "ElemBox": {
              "Min": {
                "X": 194.31348,
                "Y": -234.3555,
                "Z": -1120.9609
              },
              "Max": {
                "X": 520.3795,
                "Y": 128.1761,
                "Z": -1.4134366E-05
              },
              "IsValid": 1
            },
            "Transform": {
              "Rotation": {
                "X": 0.0,
                "Y": 0.0,
                "Z": 0.0,
                "W": 1.0,
                "SizeSquared": 1.0,
                "Size": 1.0,
                "IsNormalized": true
              },
              "Translation": {
                "X": 0.0,
                "Y": 0.0,
                "Z": 0.0
              },
              "Scale3D": {
                "X": 1.0,
                "Y": 1.0,
                "Z": 1.0
              }
            },
            "RestOffset": 0.0,
            "Name": "None",
            "bContributeToMass": true
          },
          {
            "VertexData": [
              {
                "X": 100.58405,
                "Y": -133.77135,
                "Z": -480.43652
              },
              {
                "X": 194.31348,
                "Y": -172.59532,
                "Z": -480.43655
              },
              {
                "X": 194.31348,
                "Y": -172.5954,
                "Z": -4.775607E-05
              },
              {
                "X": 100.58405,
                "Y": -133.77142,
                "Z": -4.143084E-05
              },
              {
                "X": 190.47212,
                "Y": 201.69548,
                "Z": -480.43643
              },
              {
                "X": 367.9639,
                "Y": 128.17601,
                "Z": -480.43646
              },
              {
                "X": 313.12466,
                "Y": 33.191586,
                "Z": -1.4134366E-05
              },
              {
                "X": 162.08525,
                "Y": 95.75415,
                "Z": -4.00372E-06
              },
              {
                "X": 100.58405,
                "Y": -133.77124,
                "Z": -1120.9609
              },
              {
                "X": 194.31348,
                "Y": -172.59523,
                "Z": -1120.9609
              },
              {
                "X": 190.47212,
                "Y": 201.69557,
                "Z": -1120.9608
              },
              {
                "X": 367.9639,
                "Y": 128.1761,
                "Z": -1120.9608
              }
            ],
            "ElemBox": {
              "Min": {
                "X": 100.58405,
                "Y": -172.5954,
                "Z": -1120.9609
              },
              "Max": {
                "X": 367.9639,
                "Y": 201.69557,
                "Z": -4.00372E-06
              },
              "IsValid": 1
            },
            "Transform": {
              "Rotation": {
                "X": 0.0,
                "Y": 0.0,
                "Z": 0.0,
                "W": 1.0,
                "SizeSquared": 1.0,
                "Size": 1.0,
                "IsNormalized": true
              },
              "Translation": {
                "X": 0.0,
                "Y": 0.0,
                "Z": 0.0
              },
              "Scale3D": {
                "X": 1.0,
                "Y": 1.0,
                "Z": 1.0
              }
            },
            "RestOffset": 0.0,
            "Name": "None",
            "bContributeToMass": true
          },
          {
            "VertexData": [
              {
                "X": 0.0,
                "Y": -120.52919,
                "Z": -480.43652
              },
              {
                "X": 0.0,
                "Y": -120.52927,
                "Z": -3.9273422E-05
              },
              {
                "X": 0.0,
                "Y": 226.77162,
                "Z": -480.43643
              },
              {
                "X": 0.0,
                "Y": 117.09309,
                "Z": -5.8925235E-07
              },
              {
                "X": 100.58405,
                "Y": -133.77135,
                "Z": -480.43652
              },
              {
                "X": 100.58405,
                "Y": -133.77142,
                "Z": -4.143084E-05
              },
              {
                "X": 190.47212,
                "Y": 201.69548,
                "Z": -480.43643
              },
              {
                "X": 162.08525,
                "Y": 95.75415,
                "Z": -4.00372E-06
              },
              {
                "X": 0.0,
                "Y": -120.52909,
                "Z": -1120.9609
              },
              {
                "X": 0.0,
                "Y": 226.77173,
                "Z": -1120.9608
              },
              {
                "X": 100.58405,
                "Y": -133.77124,
                "Z": -1120.9609
              },
              {
                "X": 190.47212,
                "Y": 201.69557,
                "Z": -1120.9608
              }
            ],
            "ElemBox": {
              "Min": {
                "X": 0.0,
                "Y": -133.77142,
                "Z": -1120.9609
              },
              "Max": {
                "X": 190.47212,
                "Y": 226.77173,
                "Z": -5.8925235E-07
              },
              "IsValid": 1
            },
            "Transform": {
              "Rotation": {
                "X": 0.0,
                "Y": 0.0,
                "Z": 0.0,
                "W": 1.0,
                "SizeSquared": 1.0,
                "Size": 1.0,
                "IsNormalized": true
              },
              "Translation": {
                "X": 0.0,
                "Y": 0.0,
                "Z": 0.0
              },
              "Scale3D": {
                "X": 1.0,
                "Y": 1.0,
                "Z": 1.0
              }
            },
            "RestOffset": 0.0,
            "Name": "None",
            "bContributeToMass": true
          },
          {
            "VertexData": [
              {
                "X": 735.9278,
                "Y": -509.1562,
                "Z": -480.43655
              },
              {
                "X": 388.62695,
                "Y": -509.15622,
                "Z": -0.00010258879
              },
              {
                "X": 388.62695,
                "Y": -509.15616,
                "Z": -480.43658
              },
              {
                "X": 626.2493,
                "Y": -509.15628,
                "Z": -0.00010224569
              },
              {
                "X": 375.38483,
                "Y": -408.5721,
                "Z": -480.43658
              },
              {
                "X": 375.38483,
                "Y": -408.5722,
                "Z": -8.620157E-05
              },
              {
                "X": 710.8517,
                "Y": -318.68408,
                "Z": -480.43652
              },
              {
                "X": 604.9104,
                "Y": -347.071,
                "Z": -7.5900745E-05
              },
              {
                "X": 375.38483,
                "Y": -408.57202,
                "Z": -1120.9609
              },
              {
                "X": 388.62695,
                "Y": -509.15604,
                "Z": -1120.9609
              },
              {
                "X": 710.8517,
                "Y": -318.684,
                "Z": -1120.9608
              },
              {
                "X": 735.9278,
                "Y": -509.1561,
                "Z": -1120.9609
              }
            ],
            "ElemBox": {
              "Min": {
                "X": 375.38483,
                "Y": -509.15628,
                "Z": -1120.9609
              },
              "Max": {
                "X": 735.9278,
                "Y": -318.684,
                "Z": -7.5900745E-05
              },
              "IsValid": 1
            },
            "Transform": {
              "Rotation": {
                "X": 0.0,
                "Y": 0.0,
                "Z": 0.0,
                "W": 1.0,
                "SizeSquared": 1.0,
                "Size": 1.0,
                "IsNormalized": true
              },
              "Translation": {
                "X": 0.0,
                "Y": 0.0,
                "Z": 0.0
              },
              "Scale3D": {
                "X": 1.0,
                "Y": 1.0,
                "Z": 1.0
              }
            },
            "RestOffset": 0.0,
            "Name": "None",
            "bContributeToMass": true
          }
        ]
      },
      "DefaultInstance": {
        "ObjectType": "ECC_WorldStatic",
        "CollisionProfileName": "BlockAll",
        "CollisionResponses": {
          "ResponseArray": [
            {
              "Channel": "Damage",
              "Response": "ECR_Overlap"
            }
          ]
        }
      }
    }
  },
  {
    "Type": "NavCollision",
    "Name": "NavCollision_2",
    "Outer": "CanalWall1a",
    "CookedFormatData": {
      "NavCollision_X": {
        "BulkDataFlag": "BULKDATA_ForceInlinePayload",
        "ElementCount": 3357,
        "SizeOnDisk": 3357,
        "OffsetInFile": "0x6C71"
      }
    }
  },
  {
    "Type": "StaticMesh",
    "Name": "CanalWall1a",
    "Properties": {
      "StaticMaterials": [
        {
          "MaterialInterface": {
            "ObjectName": "MaterialInstanceConstant CanalRepeating",
            "ObjectPath": "War/Content/Materials/Environment/Props/CanalRepeating.0"
          },
          "MaterialSlotName": "CanalPillar_low0",
          "ImportedMaterialSlotName": "CanalWall.001",
          "UVChannelData": {
            "bInitialized": true,
            "bOverrideDensities": false,
            "LocalUVDensities": 702.5012,
            "LocalUVDensities": 2502.5208,
            "LocalUVDensities": 0.0,
            "LocalUVDensities": 0.0
          }
        },
        {
          "MaterialInterface": {
            "ObjectName": "MaterialInstanceConstant CanalTrims",
            "ObjectPath": "War/Content/Materials/Environment/Props/CanalTrims.0"
          },
          "MaterialSlotName": "CanalWall_low0.001",
          "ImportedMaterialSlotName": "CanalWall_low0.001",
          "UVChannelData": {
            "bInitialized": true,
            "bOverrideDensities": false,
            "LocalUVDensities": 478.84683,
            "LocalUVDensities": 2542.8916,
            "LocalUVDensities": 0.0,
            "LocalUVDensities": 0.0
          }
        }
      ],
      "LightmapUVDensity": 2515.5361,
      "LightMapResolution": 64,
      "LightMapCoordinateIndex": 1,
      "ExtendedBounds": {
        "Origin": {
          "X": 382.7381,
          "Y": -126.84091,
          "Z": -555.7275
        },
        "BoxExtent": {
          "X": 383.9462,
          "Y": 382.74286,
          "Z": 565.23346
        },
        "SphereRadius": 768.7776
      }
    },
    "BodySetup": {
      "ObjectName": "BodySetup CanalWall1a:BodySetup_1",
      "ObjectPath": "War/Content/Meshes/Environment/Towns/Walls/CanalWall1a.0"
    },
    "NavCollision": {
      "ObjectName": "NavCollision CanalWall1a:NavCollision_2",
      "ObjectPath": "War/Content/Meshes/Environment/Towns/Walls/CanalWall1a.1"
    },
    "LightingGuid": "346B1A9C-4944145C-0FBB7DAB-F8237E89",
    "RenderData": null
  }
]